substreams_firehose/__about__.py
substreams_firehose/__init__.py
substreams_firehose/__main__.py
substreams_firehose/args.py
substreams_firehose/exceptions.py
substreams_firehose/requests.py
substreams_firehose/utils.py
substreams_firehose/block_extractors/__init__.py
substreams_firehose/block_extractors/async_multi_channel.py
substreams_firehose/block_extractors/async_optimized.py
substreams_firehose/block_extractors/async_single_channel.py
substreams_firehose/block_extractors/common.py
substreams_firehose/block_processors/__init__.py
substreams_firehose/block_processors/processors.py
substreams_firehose/config/__init__.py
substreams_firehose/config/__main__.py
substreams_firehose/config/parser.py
substreams_firehose/config/dfuse/default.hjson
substreams_firehose/config/dfuse/producerpay.hjson
substreams_firehose/config/firehose/default.hjson
substreams_firehose/config/substreams/default.hjson
substreams_firehose/config/ui/__init__.py
substreams_firehose/config/ui/app.py
substreams_firehose/config/ui/forms/__init__.py
substreams_firehose/config/ui/forms/custom.py
substreams_firehose/config/ui/forms/generic.py
substreams_firehose/config/ui/forms/main.py
substreams_firehose/config/ui/forms/main_config_edit.py
substreams_firehose/config/ui/forms/stub_config_edit.py
substreams_firehose/config/ui/widgets/__init__.py
substreams_firehose/config/ui/widgets/custom.py
substreams_firehose/config/ui/widgets/input_validators.py
substreams_firehose/config/ui/widgets/inputs.py
substreams_firehose/proto/antelope/eosio/token/v1/test.proto
substreams_firehose/proto/aptos/block_output/v1/block_output.proto
substreams_firehose/proto/aptos/extractor/v1/extractor.proto
substreams_firehose/proto/aptos/tokens/v1/tokens.proto
substreams_firehose/proto/aptos/util/timestamp/timestamp.proto
substreams_firehose/proto/cosmos_proto/cosmos.proto
substreams_firehose/proto/dfuse/bstream/v1/bstream.proto
substreams_firehose/proto/dfuse/eosio/codec/v1/codec.proto
substreams_firehose-1.0.1.dist-info/METADATA
substreams_firehose-1.0.1.dist-info/WHEEL
substreams_firehose-1.0.1.dist-info/licenses/LICENSE
substreams_firehose-1.0.1.dist-info/RECORD
