Metadata-Version: 2.1
Name: substreams_firehose
Version: 1.0.1
Summary: Extract any data from the blockchain using gRPC-enabled endpoints powered by Substreams and Firehose.
Project-URL: Documentation, https://github.com/pinax-network/substreams_firehose/tree/main/docs
Project-URL: Issues, https://github.com/pinax-network/substreams_firehose/issues
Project-URL: Source, https://github.com/pinax-network/substreams_firehose
Author-email: Krow10 <23462475+Krow10@users.noreply.github.com>
License-Expression: MIT
License-File: LICENSE
Keywords: analytics,blockchain,firehose,grpc,pinax,streamingfast,substreams,thegraph
Classifier: Development Status :: 4 - Beta
Classifier: Programming Language :: Python
Classifier: Programming Language :: Python :: 3.7
Classifier: Programming Language :: Python :: 3.8
Classifier: Programming Language :: Python :: 3.9
Classifier: Programming Language :: Python :: 3.10
Classifier: Programming Language :: Python :: 3.11
Classifier: Programming Language :: Python :: Implementation :: CPython
Classifier: Programming Language :: Python :: Implementation :: PyPy
Requires-Python: >=3.7
Requires-Dist: grpcio
Requires-Dist: grpcio-reflection
Requires-Dist: grpcio-tools
Requires-Dist: hjson
Requires-Dist: npyscreen
Requires-Dist: protobuf==4.21.12
Requires-Dist: protoletariat
Requires-Dist: pygments
Requires-Dist: pylint
Requires-Dist: python-dotenv
Requires-Dist: requests-cache
